kaze/Blockchain.py
kaze/EventHub.py
kaze/Settings.py
kaze/UserPreferences.py
kaze/__init__.py
kaze/test_preferences.py
kaze/test_settings.py
kaze/Core/AssetType.py
kaze/Core/Block.py
kaze/Core/BlockBase.py
kaze/Core/Blockchain.py
kaze/Core/CoinReference.py
kaze/Core/FunctionCode.py
kaze/Core/Header.py
kaze/Core/Helper.py
kaze/Core/Mixins.py
kaze/Core/Size.py
kaze/Core/VerificationCode.py
kaze/Core/Witness.py
kaze/Core/__init__.py
kaze/Core/test_block.py
kaze/Core/test_block_hash.py
kaze/Core/test_function_code.py
kaze/Core/test_genesis_block.py
kaze/Core/State/AccountState.py
kaze/Core/State/AssetState.py
kaze/Core/State/CoinState.py
kaze/Core/State/ContractState.py
kaze/Core/State/SpentCoinState.py
kaze/Core/State/StateBase.py
kaze/Core/State/StateDescriptor.py
kaze/Core/State/StorageItem.py
kaze/Core/State/StorageKey.py
kaze/Core/State/UnspentCoinState.py
kaze/Core/State/ValidatorState.py
kaze/Core/State/__init__.py
kaze/Core/State/test_states.py
kaze/Core/TX/ClaimTransaction.py
kaze/Core/TX/EnrollmentTransaction.py
kaze/Core/TX/InvocationTransaction.py
kaze/Core/TX/IssueTransaction.py
kaze/Core/TX/MinerTransaction.py
kaze/Core/TX/PublishTransaction.py
kaze/Core/TX/RegisterTransaction.py
kaze/Core/TX/StateTransaction.py
kaze/Core/TX/Transaction.py
kaze/Core/TX/TransactionAttribute.py
kaze/Core/TX/__init__.py
kaze/Core/TX/test_transactions.py
kaze/IO/Helper.py
kaze/IO/MemoryStream.py
kaze/IO/__init__.py
kaze/Implementations/__init__.py
kaze/Implementations/Blockchains/__init__.py
kaze/Implementations/Blockchains/LevelDB/CachedScriptTable.py
kaze/Implementations/Blockchains/LevelDB/DBCollection.py
kaze/Implementations/Blockchains/LevelDB/DBPrefix.py
kaze/Implementations/Blockchains/LevelDB/DebugStorage.py
kaze/Implementations/Blockchains/LevelDB/LevelDBBlockchain.py
kaze/Implementations/Blockchains/LevelDB/TestLevelDBBlockchain.py
kaze/Implementations/Blockchains/LevelDB/__init__.py
kaze/Implementations/Blockchains/LevelDB/test_LevelDBBlockchain.py
kaze_python-0.8.9.dist-info/LICENSE.md
kaze_python-0.8.9.dist-info/METADATA
kaze_python-0.8.9.dist-info/WHEEL
kaze_python-0.8.9.dist-info/entry_points.txt
kaze_python-0.8.9.dist-info/top_level.txt
kaze_python-0.8.9.dist-info/RECORD
