Metadata-Version: 2.1
Name: kaze-python
Version: 0.8.9
Summary: Python Node and SDK for the kaze blockchain
Home-page: https://github.com/KAZEBLOCKCHAIN/kaze-python
Author: Moe Sayadi
Author-email: Moe@KAZEBLOCKCHAIN.ch
Maintainer: Ela soltani
Maintainer-email: ela@KAZEBLOCKCHAIN.ch
License: MIT license
Keywords: kaze,python,node
Platform: UNKNOWN
Classifier: Development Status :: 3 - Alpha
Classifier: Intended Audience :: Developers
Classifier: License :: OSI Approved :: MIT License
Classifier: Natural Language :: English
Classifier: Programming Language :: Python :: 3
Classifier: Programming Language :: Python :: 3.6
Classifier: Programming Language :: Python :: 3.7
Requires-Python: >=3.6
Requires-Dist: aenum (==2.1.2)
Requires-Dist: asn1crypto (==0.24.0)
Requires-Dist: astor (==0.7.1)
Requires-Dist: attrs (==18.1.0)
Requires-Dist: Automat (==0.7.0)
Requires-Dist: autopep8 (==1.3.5)
Requires-Dist: base58 (==1.0.2)
Requires-Dist: bitcoin (==1.1.42)
Requires-Dist: blessings (==1.7)
Requires-Dist: bpython (==0.17.1)
Requires-Dist: bumpversion (==0.5.3)
Requires-Dist: certifi (==2018.4.16)
Requires-Dist: cffi (==1.11.5)
Requires-Dist: chardet (==3.0.4)
Requires-Dist: colorlog (==3.1.4)
Requires-Dist: constantly (==15.1.0)
Requires-Dist: coverage (==4.5.1)
Requires-Dist: coveralls (==1.3.0)
Requires-Dist: coz-bytecode (==0.5.1)
Requires-Dist: cryptography (==2.3)
Requires-Dist: curtsies (==0.3.0)
Requires-Dist: cycler (==0.10.0)
Requires-Dist: docopt (==0.6.2)
Requires-Dist: ecdsa (==0.13)
Requires-Dist: Events (==0.3)
Requires-Dist: gevent (==1.3.5)
Requires-Dist: greenlet (==0.4.14)
Requires-Dist: hyperlink (==18.0.0)
Requires-Dist: idna (==2.7)
Requires-Dist: incremental (==17.5.0)
Requires-Dist: klein (==17.10.0)
Requires-Dist: logzero (==1.5.0)
Requires-Dist: memory-profiler (==0.52.0)
Requires-Dist: mmh3 (==2.5.1)
Requires-Dist: mock (==2.0.0)
Requires-Dist: mpmath (==1.0.0)
Requires-Dist: Kaze-boa (==0.5.1)
Requires-Dist: kaze-python-rpc (==1.0.0.0)
Requires-Dist: kazecore (==0.6.8)
Requires-Dist: pbr (==4.1.1)
Requires-Dist: peewee (==3.6.4)
Requires-Dist: pexpect (==4.6.0)
Requires-Dist: pluggy (==0.6.0)
Requires-Dist: plyvel (==1.0.5)
Requires-Dist: prompt-toolkit (==2.0.3)
Requires-Dist: psutil (==5.4.6)
Requires-Dist: py (==1.5.4)
Requires-Dist: pycodestyle (==2.4.0)
Requires-Dist: pycparser (==2.18)
Requires-Dist: Pygments (==2.2.0)
Requires-Dist: pymitter (==0.2.3)
Requires-Dist: Pympler (==0.5)
Requires-Dist: pyparsing (==2.2.0)
Requires-Dist: python-dateutil (==2.7.3)
Requires-Dist: pytz (==2018.5)
Requires-Dist: requests (==2.19.1)
Requires-Dist: scrypt (==0.8.6)
Requires-Dist: six (==1.11.0)
Requires-Dist: tqdm (==4.23.4)
Requires-Dist: Twisted (==18.7.0)
Requires-Dist: typing (==3.6.4)
Requires-Dist: urllib3 (==1.23)
Requires-Dist: virtualenv (==16.0.0)
Requires-Dist: wcwidth (==0.1.7)
Requires-Dist: Werkzeug (==0.14.1)
Requires-Dist: zope.interface (==4.5.0)
